{
  "main": {
    "id": "6330f202e6e907c9",
    "type": "split",
    "children": [
      {
        "id": "289cdfee8e0ca402",
        "type": "tabs",
        "children": [
          {
            "id": "cb7049312a3d1b8b",
            "type": "leaf",
            "state": {
              "type": "markdown",
              "state": {
                "file": "JavaWeb/JMX.md",
                "mode": "source",
                "source": false
              }
            }
          }
        ]
      }
    ],
    "direction": "vertical"
  },
  "left": {
    "id": "0f6615bd372735ba",
    "type": "split",
    "children": [
      {
        "id": "5a16dae0bafc673d",
        "type": "tabs",
        "children": [
          {
            "id": "ee396f47eacbb472",
            "type": "leaf",
            "state": {
              "type": "file-explorer",
              "state": {
                "sortOrder": "byCreatedTimeReverse"
              }
            }
          },
          {
            "id": "053be81411392fe9",
            "type": "leaf",
            "state": {
              "type": "search",
              "state": {
                "query": "",
                "matchingCase": true,
                "explainSearch": false,
                "collapseAll": false,
                "extraContext": false,
                "sortOrder": "alphabetical"
              }
            }
          },
          {
            "id": "40400cd971049f91",
            "type": "leaf",
            "state": {
              "type": "starred",
              "state": {}
            }
          },
          {
            "id": "5f915fe5a3cc0fd4",
            "type": "leaf",
            "state": {
              "type": "bookmarks",
              "state": {}
            }
          }
        ]
      }
    ],
    "direction": "horizontal",
    "width": 233.5
  },
  "right": {
    "id": "e6df9437df785db9",
    "type": "split",
    "children": [
      {
        "id": "7a02db1b08c22cf4",
        "type": "tabs",
        "children": [
          {
            "id": "964ea440220124a6",
            "type": "leaf",
            "state": {
              "type": "backlink",
              "state": {
                "file": "JavaWeb/JMX.md",
                "collapseAll": false,
                "extraContext": false,
                "sortOrder": "alphabetical",
                "showSearch": false,
                "searchQuery": "",
                "backlinkCollapsed": false,
                "unlinkedCollapsed": true
              }
            }
          },
          {
            "id": "9e2f59567a3a2f91",
            "type": "leaf",
            "state": {
              "type": "outgoing-link",
              "state": {
                "file": "JavaWeb/JMX.md",
                "linksCollapsed": false,
                "unlinkedCollapsed": true
              }
            }
          },
          {
            "id": "87e5e791f2abe383",
            "type": "leaf",
            "state": {
              "type": "tag",
              "state": {
                "sortOrder": "frequency",
                "useHierarchy": true
              }
            }
          },
          {
            "id": "dbc112fdcd6519c6",
            "type": "leaf",
            "state": {
              "type": "outline",
              "state": {
                "file": "JavaWeb/JMX.md"
              }
            }
          },
          {
            "id": "1460809a051dc831",
            "type": "leaf",
            "state": {
              "type": "git-view",
              "state": {}
            }
          }
        ],
        "currentTab": 4
      }
    ],
    "direction": "horizontal",
    "width": 200,
    "collapsed": true
  },
  "left-ribbon": {
    "hiddenItems": {
      "switcher:Open quick switcher": false,
      "graph:Open graph view": false,
      "canvas:Create new canvas": false,
      "daily-notes:Open today's daily note": false,
      "templates:Insert template": false,
      "command-palette:Open command palette": false
    }
  },
  "active": "cb7049312a3d1b8b",
  "lastOpenFiles": [
    "EastWater/施肥机/Fertilizer params.md",
    "JavaWeb/JMX.md",
    "EastWater/施肥机/变量导入说明.md",
    "structure/MyConfig/Maven&Garadle.md",
    "digtalTwin/开发方案/Unity.md",
    "工作计划/2023-05/2023.05.15-05.20.md",
    "工作计划/2023-05/2023-05-15.md",
    "structure/Spirng/SpringBoot/定时任务/cron表达式.md",
    "structure/Spirng/SpringBoot/定时任务/JobDataMap.md",
    "structure/Spirng/SpringBoot/定时任务/JobExecutionContext.md",
    "structure/Spirng/SpringBoot/定时任务/org.quartz.Job.md",
    "structure/Spirng/OOM/线程阻塞问题.md",
    "structure/Spirng/Maven&Gradle/Dependencies/ALL_dependencies.md",
    "structure/Spirng/Maven&Gradle/Dependencies/FurtherInfomation/spring-boot-starter-validation.md",
    "structure/Spirng/SpringBoot/Java/Clob类.md",
    "structure/Spirng/SpringBoot/Java/入参校验.md",
    "structure/Spirng/SpringBoot/依赖注入/@RequiredArgsConstructor.md",
    "structure/Spirng/SpringBoot/依赖注入/@Inject.md",
    "structure/Spirng/SpringBoot/依赖注入/Autowired.md",
    "Temp/Untitled 1.md",
    "structure/Spirng/SpringBoot/Kotlin/Basic-syntax.md",
    "structure/Spirng/SpringBoot/Kotlin/open&final.md",
    "structure/Spirng/SpringBoot/Kotlin/coroutine.md",
    "structure/Spirng/SpringBoot/Kotlin/DataTypes.md",
    "structure/Spirng/Web/Four_ways_entends Web/NO2 Spring package.md",
    "Obsidian/Obsidain grammar/Obsidian语法.md",
    "DesginModel/Pasted image 20230520151503.png",
    "DesginModel/Pasted image 20230520151226.png",
    "structure/MyConfig",
    "structure",
    "structure/Spirng/OOM",
    "structure/Spirng/Maven&Gradle/Dependencies/FurtherInfomation",
    "structure/Spirng/Maven&Gradle/Dependencies",
    "structure/Spirng/Maven&Gradle",
    "structure/Spirng/Web/Four_ways_entends Web",
    "structure/Spirng/Web",
    "Bugs/Spring",
    "Temp",
    "Pics/tools.png",
    "plugin/unity解决方案.png",
    "Pics/Unity架构3_0.png",
    "Pics/Pasted image 20230421092731.png",
    "Pasted image 20230429143319.png",
    "Pasted image 20230429143248.png",
    "Pics/digital_twin_data.png",
    "Pics/modeling.png",
    "Untitled.canvas"
  ]
}